{
  "$schema": "https://ui.shadcn.com/schema/registry-item.json",
  "name": "portfolio-mission-and-values-grid-of-core-values",
  "type": "registry:block",
  "registryDependencies": [],
  "files": [
    {
      "path": "registry/default/blocks/portfolio-mission-and-values-grid-of-core-values.tsx",
      "content": "import {\r\r\n  HeartHandshake,\r\r\n  Lightbulb,\r\r\n  Shield,\r\r\n  Users,\r\r\n  Target,\r\r\n  RefreshCw,\r\r\n  PackageOpen,\r\r\n  Sparkles,\r\r\n  Globe,\r\r\n} from \"lucide-react\";\r\r\n\r\r\nexport default function MissionAndValuesGrid() {\r\r\n  const values = [\r\r\n    {\r\r\n      title: \"Innovation\",\r\r\n      description:\r\r\n        \"We continuously challenge assumptions and explore new possibilities.\",\r\r\n      icon: <Lightbulb className=\"h-6 w-6\" />,\r\r\n    },\r\r\n    {\r\r\n      title: \"Integrity\",\r\r\n      description:\r\r\n        \"We operate with honesty, transparency, and ethical responsibility.\",\r\r\n      icon: <Shield className=\"h-6 w-6\" />,\r\r\n    },\r\r\n    {\r\r\n      title: \"Collaboration\",\r\r\n      description:\r\r\n        \"We bring diverse perspectives together to achieve extraordinary results.\",\r\r\n      icon: <Users className=\"h-6 w-6\" />,\r\r\n    },\r\r\n    {\r\r\n      title: \"Excellence\",\r\r\n      description: \"We strive for outstanding quality in everything we create.\",\r\r\n      icon: <Sparkles className=\"h-6 w-6\" />,\r\r\n    },\r\r\n    {\r\r\n      title: \"Adaptability\",\r\r\n      description: \"We embrace change and evolve to meet new challenges.\",\r\r\n      icon: <RefreshCw className=\"h-6 w-6\" />,\r\r\n    },\r\r\n    {\r\r\n      title: \"Empathy\",\r\r\n      description:\r\r\n        \"We design with a deep understanding of human needs and experiences.\",\r\r\n      icon: <HeartHandshake className=\"h-6 w-6\" />,\r\r\n    },\r\r\n    {\r\r\n      title: \"Purpose\",\r\r\n      description: \"We focus on creating meaningful impact that matters.\",\r\r\n      icon: <Target className=\"h-6 w-6\" />,\r\r\n    },\r\r\n    {\r\r\n      title: \"Transparency\",\r\r\n      description:\r\r\n        \"We communicate openly and honestly with clients and team members.\",\r\r\n      icon: <PackageOpen className=\"h-6 w-6\" />,\r\r\n    },\r\r\n    {\r\r\n      title: \"Sustainability\",\r\r\n      description:\r\r\n        \"We consider long-term environmental and social impact in our work.\",\r\r\n      icon: <Globe className=\"h-6 w-6\" />,\r\r\n    },\r\r\n  ];\r\r\n\r\r\n  return (\r\r\n    <section className=\"py-16 md:py-24\">\r\r\n      <div className=\"container mx-auto px-4 md:px-6 2xl:max-w-[1400px]\">\r\r\n        {/* Header */}\r\r\n        <div className=\"mb-16 text-center\">\r\r\n          <h2 className=\"mb-4 text-3xl font-bold tracking-tight sm:text-4xl md:text-5xl\">\r\r\n            Our Core Values\r\r\n          </h2>\r\r\n          <p className=\"text-muted-foreground mx-auto max-w-3xl text-lg\">\r\r\n            These principles guide our decisions, shape our culture, and define\r\r\n            how we collaborate with our clients.\r\r\n          </p>\r\r\n        </div>\r\r\n\r\r\n        {/* Values Grid */}\r\r\n        <div className=\"grid gap-6 sm:grid-cols-2 md:grid-cols-3\">\r\r\n          {values.map((value, index) => (\r\r\n            <div\r\r\n              key={index}\r\r\n              className=\"bg-card flex flex-col rounded-lg border p-6 shadow-sm transition-all hover:shadow-md\"\r\r\n            >\r\r\n              <div className=\"bg-primary/10 text-primary mb-4 flex h-12 w-12 items-center justify-center rounded-md\">\r\r\n                {value.icon}\r\r\n              </div>\r\r\n              <h3 className=\"mb-2 text-xl font-semibold\">{value.title}</h3>\r\r\n              <p className=\"text-muted-foreground\">{value.description}</p>\r\r\n            </div>\r\r\n          ))}\r\r\n        </div>\r\r\n      </div>\r\r\n    </section>\r\r\n  );\r\r\n}\r\r\n",
      "type": "registry:block"
    }
  ],
  "meta": {
    "tags": [
      "portfolio-mission-and-values"
    ]
  }
}